crudly/__init__.py
crudly/crudly.py
crudly/exceptions.py
crudly-2025.2.22.dist-info/METADATA
crudly-2025.2.22.dist-info/WHEEL
crudly-2025.2.22.dist-info/licenses/LICENSE
crudly-2025.2.22.dist-info/RECORD
