Metadata-Version: 2.4
Name: crudly
Version: 2025.2.22
Summary: Super simple FastAPI CRUD generator for SQLModel ORM
Project-URL: Homepage, https://github.com/amozebus/crudly
Project-URL: Repository, https://github.com/amozebus/crudly.git
Author-email: amozebus <amozebus@gmail.com>
License-Expression: MIT
License-File: LICENSE
Requires-Python: >=3.10
Requires-Dist: fastapi>=0.115.8
Requires-Dist: sqlmodel>=0.0.22
Provides-Extra: dev
Requires-Dist: black; extra == 'dev'
